MANIFEST.in
README.rst
requirements.txt
setup.cfg
setup.py
kotti_history/__init__.py
kotti_history/__init__.pyc
kotti_history/decorators.py
kotti_history/decorators.pyc
kotti_history/fanstatic.py
kotti_history/fanstatic.pyc
kotti_history/populate.py
kotti_history/populate.pyc
kotti_history/resources.py
kotti_history/resources.pyc
kotti_history.egg-info/PKG-INFO
kotti_history.egg-info/SOURCES.txt
kotti_history.egg-info/dependency_links.txt
kotti_history.egg-info/entry_points.txt
kotti_history.egg-info/not-zip-safe
kotti_history.egg-info/requires.txt
kotti_history.egg-info/top_level.txt
kotti_history/alembic/script.py.mako
kotti_history/alembic/versions/.gitkeep
kotti_history/locale/.gitkeep
kotti_history/static/incrementer.js
kotti_history/static/scripts.js
kotti_history/static/scripts.min.js
kotti_history/static/styles.css
kotti_history/static/styles.min.css
kotti_history/templates/history.pt
kotti_history/templates/recorder.pt
kotti_history/templates/searches.pt
kotti_history/tests/conftest.py
kotti_history/tests/test_functional.py
kotti_history/tests/test_resources.py
kotti_history/tests/test_view.py
kotti_history/views/__init__.py
kotti_history/views/__init__.pyc
kotti_history/views/view.py
kotti_history/views/view.pyc